physical_const/__init__.py
physical_const-0.1.2.dist-info/METADATA
physical_const-0.1.2.dist-info/WHEEL
physical_const-0.1.2.dist-info/top_level.txt
physical_const-0.1.2.dist-info/RECORD
