Metadata-Version: 2.1
Name: physical-const
Version: 0.1.2
Summary: Physical constants library
Home-page: https://github.com/PawekPL/python-physical-constants
Author: Paweł "Pawek" Fiszer
License: MIT
Platform: UNKNOWN
